enthusiast_agent_tool_calling/__init__.py
enthusiast_agent_tool_calling/base_tool_calling_agent.py
enthusiast_agent_tool_calling-1.0.0.dist-info/METADATA
enthusiast_agent_tool_calling-1.0.0.dist-info/WHEEL
enthusiast_agent_tool_calling-1.0.0.dist-info/RECORD
