Metadata-Version: 2.4
Name: enthusiast-agent-tool-calling
Version: 1.0.0
Summary: Base implementation of a Tool Calling agent for Enthusiast
Author: Damian Sowiński
Author-email: damian.sowinski@upsidelab.io
Requires-Python: >=3.10,<4
Classifier: Programming Language :: Python :: 3
Classifier: Programming Language :: Python :: 3.10
Classifier: Programming Language :: Python :: 3.11
Classifier: Programming Language :: Python :: 3.12
Classifier: Programming Language :: Python :: 3.13
Classifier: Programming Language :: Python :: 3.14
Requires-Dist: enthusiast-common (>=1.4.0,<2.0.0)
Requires-Dist: langchain (>=0.3.26,<0.4.0)
